<annotation>
	<folder>images</folder>
	<filename>0198.jpg</filename>
	<path>/Volumes/Data/Custom-Object-Detection/images/0198.jpg</path>
	<source>
		<database>Unknown</database>
	</source>
	<size>
		<width>457</width>
		<height>640</height>
		<depth>3</depth>
	</size>
	<segmented>0</segmented>
	<object>
		<name>sour_cream</name>
		<pose>Unspecified</pose>
		<truncated>0</truncated>
		<difficult>0</difficult>
		<bndbox>
			<xmin>282</xmin>
			<ymin>160</ymin>
			<xmax>320</xmax>
			<ymax>196</ymax>
		</bndbox>
	</object>
	<object>
		<name>sour_cream</name>
		<pose>Unspecified</pose>
		<truncated>0</truncated>
		<difficult>0</difficult>
		<bndbox>
			<xmin>369</xmin>
			<ymin>165</ymin>
			<xmax>401</xmax>
			<ymax>200</ymax>
		</bndbox>
	</object>
	<object>
		<name>soy_sauce</name>
		<pose>Unspecified</pose>
		<truncated>0</truncated>
		<difficult>0</difficult>
		<bndbox>
			<xmin>133</xmin>
			<ymin>70</ymin>
			<xmax>164</xmax>
			<ymax>136</ymax>
		</bndbox>
	</object>
	<object>
		<name>sauce</name>
		<pose>Unspecified</pose>
		<truncated>0</truncated>
		<difficult>0</difficult>
		<bndbox>
			<xmin>102</xmin>
			<ymin>284</ymin>
			<xmax>144</xmax>
			<ymax>362</ymax>
		</bndbox>
	</object>
</annotation>
